odoo/addons/l10n_cl_sii/README.rst
odoo/addons/l10n_cl_sii/__init__.py
odoo/addons/l10n_cl_sii/__manifest__.py
odoo/addons/l10n_cl_sii/i18n/es_CL.po
odoo/addons/l10n_cl_sii/i18n/l10n_cl_sii.pot
odoo/addons/l10n_cl_sii/readme/CONTRIBUTORS.rst
odoo/addons/l10n_cl_sii/readme/DESCRIPTION.rst
odoo/addons/l10n_cl_sii/readme/USAGE.rst
odoo/addons/l10n_cl_sii/static/description/icon.png
odoo/addons/l10n_cl_sii/static/description/index.html
odoo/addons/l10n_cl_sii/views/menuitem.xml
odoo12_addon_l10n_cl_sii-12.0.1.0.0.99.dev10.dist-info/METADATA
odoo12_addon_l10n_cl_sii-12.0.1.0.0.99.dev10.dist-info/WHEEL
odoo12_addon_l10n_cl_sii-12.0.1.0.0.99.dev10.dist-info/top_level.txt
odoo12_addon_l10n_cl_sii-12.0.1.0.0.99.dev10.dist-info/RECORD
